ethproxy/__init__.py
ethproxy/cli.py
ethproxy/logger.py
ethproxy/main.py
ethproxy/settings.py
ethproxy/mining_libs/__init__.py
ethproxy/mining_libs/client_service.py
ethproxy/mining_libs/getwork_listener.py
ethproxy/mining_libs/jobs.py
ethproxy/stratum/__init__.py
ethproxy/stratum/connection_registry.py
ethproxy/stratum/custom_exceptions.py
ethproxy/stratum/event_handler.py
ethproxy/stratum/helpers.py
ethproxy/stratum/http_transport.py
ethproxy/stratum/jsonical.py
ethproxy/stratum/protocol.py
ethproxy/stratum/pubsub.py
ethproxy/stratum/semaphore.py
ethproxy/stratum/server.py
ethproxy/stratum/services.py
ethproxy/stratum/socket_transport.py
ethproxy/stratum/socksclient.py
ethproxy/stratum/stats.py
ethproxy/stratum/storage.py
ethproxy/stratum/websocket_transport.py
ethproxy-1.0.3.dist-info/DESCRIPTION.rst
ethproxy-1.0.3.dist-info/METADATA
ethproxy-1.0.3.dist-info/RECORD
ethproxy-1.0.3.dist-info/WHEEL
ethproxy-1.0.3.dist-info/entry_points.txt
ethproxy-1.0.3.dist-info/metadata.json
ethproxy-1.0.3.dist-info/top_level.txt
ethproxy-1.0.3.dist-info/zip-safe
tests/__init__.py
tests/test_main.py
