Metadata-Version: 2.0
Name: ethproxy
Version: 1.0.3
Summary: Ethereum stratum proxy
Home-page: https://github.com/narfman0/eth-proxy
Author: Jon Robison
Author-email: narfman0@gmail.com
License: GPL2 license
Keywords: crypto eth ethereum proxy
Platform: UNKNOWN
Classifier: Development Status :: 4 - Beta
Classifier: Intended Audience :: Developers
Classifier: License :: OSI Approved :: GNU General Public License v2 (GPLv2)
Classifier: Natural Language :: English
Classifier: Programming Language :: Python :: 2
Classifier: Programming Language :: Python :: 2.7
Classifier: Programming Language :: Python :: 3
Classifier: Programming Language :: Python :: 3.6
Requires-Dist: Twisted (==16.1.1)
Requires-Dist: zope.interface (==4.1.3)
